ibkr_mcp_server/__init__.py
ibkr_mcp_server/__main__.py
ibkr_mcp_server/client.py
ibkr_mcp_server/config.py
ibkr_mcp_server/main.py
ibkr_mcp_server/tools.py
ibkr_mcp_server/utils.py
iflow_mcp_arjundivecha_ibkr_mcp_server-1.0.1.dist-info/METADATA
iflow_mcp_arjundivecha_ibkr_mcp_server-1.0.1.dist-info/WHEEL
iflow_mcp_arjundivecha_ibkr_mcp_server-1.0.1.dist-info/entry_points.txt
iflow_mcp_arjundivecha_ibkr_mcp_server-1.0.1.dist-info/licenses/LICENSE
iflow_mcp_arjundivecha_ibkr_mcp_server-1.0.1.dist-info/RECORD
