Metadata-Version: 2.4
Name: iflow-mcp_arjundivecha_ibkr-mcp-server
Version: 1.0.1
Summary: Interactive Brokers MCP Server for Claude Desktop/Code
Project-URL: Homepage, https://github.com/arjundivecha/ibkr-mcp-server
Project-URL: Repository, https://github.com/arjundivecha/ibkr-mcp-server
Project-URL: Issues, https://github.com/arjundivecha/ibkr-mcp-server/issues
Project-URL: Changelog, https://github.com/arjundivecha/ibkr-mcp-server/blob/main/CHANGELOG.md
Author-email: Arjun Divecha <your.email@example.com>
License-Expression: MIT
License-File: LICENSE
Classifier: Development Status :: 4 - Beta
Classifier: Intended Audience :: Financial and Insurance Industry
Classifier: License :: OSI Approved :: MIT License
Classifier: Programming Language :: Python :: 3
Classifier: Programming Language :: Python :: 3.10
Classifier: Programming Language :: Python :: 3.11
Classifier: Programming Language :: Python :: 3.12
Classifier: Topic :: Office/Business :: Financial :: Investment
Requires-Python: >=3.10
Requires-Dist: click>=8.0.0
Requires-Dist: ib-async>=0.9.86
Requires-Dist: mcp>=1.0.0
Requires-Dist: pydantic>=2.0.0
Requires-Dist: python-dotenv>=1.0.0
Requires-Dist: rich>=13.0.0
Provides-Extra: dev
Requires-Dist: black>=23.0.0; extra == 'dev'
Requires-Dist: coverage[toml]>=7.0.0; extra == 'dev'
Requires-Dist: isort>=5.12.0; extra == 'dev'
Requires-Dist: mypy>=1.0.0; extra == 'dev'
Requires-Dist: pre-commit>=3.0.0; extra == 'dev'
Requires-Dist: pytest-asyncio>=0.21.0; extra == 'dev'
Requires-Dist: pytest-mock>=3.10.0; extra == 'dev'
Requires-Dist: pytest>=7.0.0; extra == 'dev'
